openziti/__init__.py
openziti/__main__.py
openziti/__meta__.py
openziti/tests/__init__.py
openziti/tests/__main__.py
openziti/tests/test_documentation.py
openziti/tests/test_openziti.py
openziti_edge-0.1.0.dist-info/LICENSE
openziti_edge-0.1.0.dist-info/METADATA
openziti_edge-0.1.0.dist-info/WHEEL
openziti_edge-0.1.0.dist-info/top_level.txt
openziti_edge-0.1.0.dist-info/RECORD
