Metadata-Version: 2.1
Name: openziti-edge
Version: 0.1.0
Summary: A short description for your project.
Home-page: 
Author: NetFoundry
Author-email: support@netfoundry.io
License: UNKNOWN
Platform: any
Classifier: Development Status :: 3 - Alpha
Classifier: Intended Audience :: Developers
Classifier: License :: OSI Approved :: GNU General Public License (GPL)
Classifier: Operating System :: OS Independent
Classifier: Programming Language :: Python
Classifier: Programming Language :: Python :: 3
Classifier: Programming Language :: Python :: 3.3
Classifier: Programming Language :: Python :: 3.4
Classifier: Programming Language :: Python :: 3.5
Classifier: Topic :: Software Development :: Libraries
License-File: LICENSE
Provides-Extra: dev
Requires-Dist: python-boilerplate[dev] ; extra == 'dev'
